<AML>
 <Item type="ItemType" id="2826F2403689438295EDBF60BEAE7C74" action="add">
  <allow_private_permission>1</allow_private_permission>
  <auto_search>0</auto_search>
  <close_icon>../images/SimpleMCO.svg</close_icon>
  <enforce_discovery>1</enforce_discovery>
  <hide_where_used>0</hide_where_used>
  <implementation_type>table</implementation_type>
  <instance_data>SIMPLE_MCO</instance_data>
  <is_dependent>0</is_dependent>
  <is_relationship>0</is_relationship>
  <is_versionable>0</is_versionable>
  <label xml:lang="en">MCO</label>
  <label_plural xml:lang="en">MCOs</label_plural>
  <large_icon>../images/SimpleMCO.svg</large_icon>
  <open_icon>../images/SimpleMCO.svg</open_icon>
  <revisions keyed_name="Default" type="Revision">7FE395DD8B9F4E1090756A34B733D75E</revisions>
  <show_parameters_tab>0</show_parameters_tab>
  <structure_view>tabs on</structure_view>
  <unlock_on_logout>0</unlock_on_logout>
  <use_src_access>0</use_src_access>
  <name>Simple MCO</name>
  <Relationships>
   <Item type="DiscussionTemplate" id="64985F4606C44B088243484FE600B255" action="add">
    <file_selection_depth>2</file_selection_depth>
    <item_selection_depth>2</item_selection_depth>
    <sort_order>128</sort_order>
    <source_id keyed_name="Simple MCO" type="ItemType" name="Simple MCO">2826F2403689438295EDBF60BEAE7C74</source_id>
    <visibility_supported>1</visibility_supported>
    <Relationships>
     <Item type="FeedTemplate" id="C285E2CC168E4BCDAD8BA44DA320EE33" action="add">
      <feed_type>Board</feed_type>
      <reference>this</reference>
      <sort_order>128</sort_order>
      <source_id keyed_name="64985F4606C44B088243484FE600B255" type="DiscussionTemplate">64985F4606C44B088243484FE600B255</source_id>
      <Relationships>
       <Item type="FileSelectorTemplate" id="B891576D3C69460BB717EBE7303EFDD2" action="add">
        <filter>7869D76D50ED4BD4985BECB20B1102F7|992B142FCE6C4EF8B71417220CD7E92D|50AF497B7A114235979F882CEC8EFDF6|8A85DD9A6E0346F5AE423314E3650041</filter>
        <reference><![CDATA[Simple MCO File(related_id)]]></reference>
        <sort_order>128</sort_order>
        <source_id keyed_name="C285E2CC168E4BCDAD8BA44DA320EE33" type="FeedTemplate">C285E2CC168E4BCDAD8BA44DA320EE33</source_id>
        <tooltip_template xml:lang="en">File ${File:filename} from ${ItemType:label} ${Item:keyed_name}</tooltip_template>
       </Item>
      </Relationships>
     </Item>
     <Item type="FeedTemplate" id="A87BEA2AA28C4551B811B8700B94740D" action="add">
      <feed_type>Discussion</feed_type>
      <reference>Simple MCO Part(related_id)</reference>
      <sort_order>256</sort_order>
      <source_id keyed_name="64985F4606C44B088243484FE600B255" type="DiscussionTemplate">64985F4606C44B088243484FE600B255</source_id>
     </Item>
     <Item type="DiscussionTemplateView" id="DE32FCB0624041B2926358A2688BF509" action="add">
      <client>js</client>
      <related_id keyed_name="B81B19CB2A81445CB1A64ED015E1A127" type="SSVCPresentationConfiguration">
       <Item type="SSVCPresentationConfiguration" id="B81B19CB2A81445CB1A64ED015E1A127" action="add">
        <discussion_panel_behavior>discPanelOff</discussion_panel_behavior>
        <form_tooltip_template xml:lang="en">Form of ${ItemType:label} ${Item:keyed_name}</form_tooltip_template>
        <sm_template keyed_name="F1E9620C1AB3408588708B68E18D51DE" type="SecureMessageViewTemplate">F1E9620C1AB3408588708B68E18D51DE</sm_template>
        <name>B81B19CB2A81445CB1A64ED015E1A127</name>
       </Item>
      </related_id>
      <sort_order>128</sort_order>
      <source_id keyed_name="64985F4606C44B088243484FE600B255" type="DiscussionTemplate">64985F4606C44B088243484FE600B255</source_id>
     </Item>
    </Relationships>
   </Item>
   <Item type="ITPresentationConfiguration" id="63CCF4A174C5496195B9FB24404CE071" action="add">
    <client>js</client>
    <related_id keyed_name="700FBB9F13D9444E97FCAC19CDD62C7B" type="PresentationConfiguration">700FBB9F13D9444E97FCAC19CDD62C7B</related_id>
    <sort_order>128</sort_order>
    <source_id keyed_name="Simple MCO" type="ItemType" name="Simple MCO">2826F2403689438295EDBF60BEAE7C74</source_id>
   </Item>
   <Item type="Property" id="520B7C980BC949B284F539C3D400CFC1" action="add">
    <column_alignment>left</column_alignment>
    <column_width>120</column_width>
    <data_source keyed_name="Change Categories">40CF856AEF07402C971EA764EE980657</data_source>
    <data_type>list</data_type>
    <default_value xml:lang="en">Phase In</default_value>
    <is_hidden>0</is_hidden>
    <is_hidden2>0</is_hidden2>
    <is_indexed>0</is_indexed>
    <is_keyed>0</is_keyed>
    <is_multi_valued>0</is_multi_valued>
    <is_required>0</is_required>
    <label xml:lang="en">Change Category</label>
    <range_inclusive>0</range_inclusive>
    <readonly>0</readonly>
    <sort_order>896</sort_order>
    <source_id keyed_name="Simple MCO" type="ItemType" name="Simple MCO">2826F2403689438295EDBF60BEAE7C74</source_id>
    <stored_length>64</stored_length>
    <track_history>0</track_history>
    <name>change_category</name>
   </Item>
   <Item type="Property" id="3540E302B2B14F08AB4CA3D457491CCD" action="add">
    <column_alignment>left</column_alignment>
    <column_width>300</column_width>
    <data_type>text</data_type>
    <is_hidden>1</is_hidden>
    <is_hidden2>1</is_hidden2>
    <is_indexed>0</is_indexed>
    <is_keyed>0</is_keyed>
    <is_multi_valued>0</is_multi_valued>
    <is_required>0</is_required>
    <label xml:lang="en">Change Reason</label>
    <range_inclusive>0</range_inclusive>
    <readonly>0</readonly>
    <sort_order>1024</sort_order>
    <source_id keyed_name="Simple MCO" type="ItemType" name="Simple MCO">2826F2403689438295EDBF60BEAE7C74</source_id>
    <track_history>0</track_history>
    <name>change_reason</name>
   </Item>
   <Item type="Property" id="8390138695A94796A941DD54C7941467" action="add">
    <column_alignment>left</column_alignment>
    <column_width>200</column_width>
    <data_type>string</data_type>
    <is_hidden>0</is_hidden>
    <is_hidden2>0</is_hidden2>
    <is_indexed>0</is_indexed>
    <is_keyed>0</is_keyed>
    <is_multi_valued>0</is_multi_valued>
    <is_required>0</is_required>
    <label xml:lang="en">Change Description</label>
    <range_inclusive>0</range_inclusive>
    <readonly>0</readonly>
    <sort_order>256</sort_order>
    <source_id keyed_name="Simple MCO" type="ItemType" name="Simple MCO">2826F2403689438295EDBF60BEAE7C74</source_id>
    <stored_length>1024</stored_length>
    <track_history>0</track_history>
    <name>description</name>
   </Item>
   <Item type="Property" id="88B55ACC92D646D581DDA4565855635B" action="add">
    <column_alignment>left</column_alignment>
    <column_width>100</column_width>
    <data_source keyed_name="Simple MCO">AAF71D8E658E4EFBA36B81941A3851C7</data_source>
    <data_type>sequence</data_type>
    <is_hidden>0</is_hidden>
    <is_hidden2>0</is_hidden2>
    <is_indexed>0</is_indexed>
    <is_keyed>0</is_keyed>
    <is_multi_valued>0</is_multi_valued>
    <is_required>0</is_required>
    <keyed_name_order>1</keyed_name_order>
    <label xml:lang="en">MCO Number</label>
    <order_by>1</order_by>
    <range_inclusive>0</range_inclusive>
    <readonly>0</readonly>
    <sort_order>128</sort_order>
    <source_id keyed_name="Simple MCO" type="ItemType" name="Simple MCO">2826F2403689438295EDBF60BEAE7C74</source_id>
    <track_history>0</track_history>
    <name>item_number</name>
   </Item>
   <Item type="Property" id="1770D263011D414CBD6B9F9670CD342E" action="add">
    <column_alignment>left</column_alignment>
    <column_width>120</column_width>
    <data_type>date</data_type>
    <is_hidden>1</is_hidden>
    <is_hidden2>1</is_hidden2>
    <is_indexed>0</is_indexed>
    <is_keyed>0</is_keyed>
    <is_multi_valued>0</is_multi_valued>
    <is_required>0</is_required>
    <label xml:lang="en">Release Date</label>
    <pattern>short_date_time</pattern>
    <range_inclusive>0</range_inclusive>
    <readonly>0</readonly>
    <sort_order>1280</sort_order>
    <source_id keyed_name="Simple MCO" type="ItemType" name="Simple MCO">2826F2403689438295EDBF60BEAE7C74</source_id>
    <track_history>0</track_history>
    <name>release_date</name>
   </Item>
   <Item type="View" id="7E9FA6CAB303457A949CFDF1B25EED72" action="add">
    <client>js</client>
    <related_id keyed_name="Simple MCO" type="Form">F067AFC1026045E799F4AAF0A7571C2C</related_id>
    <role keyed_name="World" type="Identity">
     <Item type="Identity" action="get" select="id">
      <name>World</name>
     </Item>
    </role>
    <show_ssvc>1</show_ssvc>
    <sort_order>128</sort_order>
    <source_id keyed_name="Simple MCO" type="ItemType" name="Simple MCO">2826F2403689438295EDBF60BEAE7C74</source_id>
    <type>default</type>
   </Item>
   <Item type="Item Action" id="B61A2B9121CC4C60ACF14AF43F1FD291" action="add">
    <related_id keyed_name="VC_AddItemsToBookmarks" type="Action">FD4D2BE9E2B14919BF1973842A556AFD</related_id>
    <sort_order>128</sort_order>
    <source_id keyed_name="Simple MCO" type="ItemType" name="Simple MCO">2826F2403689438295EDBF60BEAE7C74</source_id>
   </Item>
   <Item type="Item Action" id="467AD349495DB09DFCA86F91283C4734" action="add">
    <related_id keyed_name="Change Discussion Definition" type="Action">5B155B40AD8F405D812EF95BC5848214</related_id>
    <sort_order>256</sort_order>
    <source_id keyed_name="Simple MCO" type="ItemType" name="Simple MCO">2826F2403689438295EDBF60BEAE7C74</source_id>
   </Item>
   <Item type="ItemType Life Cycle" id="CE7C16FB39154B63BCDE711C29BB322F" action="add">
    <related_id keyed_name="Simple MCO" type="Life Cycle Map">9DD15121F2064DE3A797DD3FD35D81A5</related_id>
    <sort_order>128</sort_order>
    <source_id keyed_name="Simple MCO" type="ItemType" name="Simple MCO">2826F2403689438295EDBF60BEAE7C74</source_id>
   </Item>
   <Item type="Allowed Workflow" id="6A45003DFC5B43768A1D80C3532C8CFD" action="add">
    <is_default>1</is_default>
    <related_id keyed_name="Simple Change" type="Workflow Map">2482A63E43BD4E8784DA4D7350F2ACDF</related_id>
    <sort_order>128</sort_order>
    <source_id keyed_name="Simple MCO" type="ItemType" name="Simple MCO">2826F2403689438295EDBF60BEAE7C74</source_id>
   </Item>
   <Item type="TOC Access" id="8A71AEFEEA1C46488C09E3737EA0A778" action="add">
    <related_id keyed_name="Aras PLM" type="Identity">56A96DA9E981481688563E2D14D5D878</related_id>
    <sort_order>128</sort_order>
    <source_id keyed_name="Simple MCO" type="ItemType" name="Simple MCO">2826F2403689438295EDBF60BEAE7C74</source_id>
    <category>Change Management</category>
   </Item>
   <Item type="Client Event" id="5EA877CB4C4145A08010A6FD6CFDD10A" action="add">
    <client_event>OnAfterNew</client_event>
    <related_id keyed_name="PE_SetOriginator" type="Method">
     <Item type="Method" action="get" select="id">
      <name>PE_SetOriginator</name>
     </Item>
    </related_id>
    <sort_order>128</sort_order>
    <source_id keyed_name="Simple MCO" type="ItemType" name="Simple MCO">2826F2403689438295EDBF60BEAE7C74</source_id>
   </Item>
   <Item type="Can Add" id="199EC8508D0C440683A0648C41CEEFCF" action="add">
    <can_add>1</can_add>
    <related_id keyed_name="World" type="Identity">
     <Item type="Identity" action="get" select="id">
      <name>World</name>
     </Item>
    </related_id>
    <sort_order>128</sort_order>
    <source_id keyed_name="Simple MCO" type="ItemType" name="Simple MCO">2826F2403689438295EDBF60BEAE7C74</source_id>
   </Item>
   <Item type="Allowed Permission" id="03F71F7D555F429C8176F74E5C9E8678" action="add">
    <is_default>1</is_default>
    <related_id keyed_name="New Change" type="Permission">8DEF7FAAC789435B9A56E70FB1B24557</related_id>
    <sort_order>128</sort_order>
    <source_id keyed_name="Simple MCO" type="ItemType" name="Simple MCO">2826F2403689438295EDBF60BEAE7C74</source_id>
   </Item>
  </Relationships>
 </Item>
 <Item type="ItemType" id="2826F2403689438295EDBF60BEAE7C74" action="edit">
  <Relationships>
   <Item type="Property" action="edit" where="source_id='2826F2403689438295EDBF60BEAE7C74' and name='created_on'">
    <column_alignment>left</column_alignment>
    <column_width>120</column_width>
    <data_type>date</data_type>
    <is_hidden>1</is_hidden>
    <is_hidden2>1</is_hidden2>
    <is_indexed>0</is_indexed>
    <is_keyed>0</is_keyed>
    <is_multi_valued>0</is_multi_valued>
    <is_required>1</is_required>
    <label xml:lang="en">Date Originated</label>
    <pattern>short_date_time</pattern>
    <range_inclusive>0</range_inclusive>
    <readonly>1</readonly>
    <sort_order>1152</sort_order>
    <source_id keyed_name="Simple MCO" type="ItemType" name="Simple MCO">2826F2403689438295EDBF60BEAE7C74</source_id>
    <track_history>0</track_history>
    <name>created_on</name>
   </Item>
   <Item type="Property" action="edit" where="source_id='2826F2403689438295EDBF60BEAE7C74' and name='managed_by_id'">
    <column_alignment>left</column_alignment>
    <column_width>120</column_width>
    <data_source keyed_name="Identity" type="ItemType" name="Identity">E582AB17663F4EF28460015B2BE9E094</data_source>
    <data_type>item</data_type>
    <default_value xml:lang="en">80727DB851A94DBCB10419D30ED69F9F</default_value>
    <is_hidden>0</is_hidden>
    <is_hidden2>0</is_hidden2>
    <is_indexed>0</is_indexed>
    <is_keyed>0</is_keyed>
    <is_multi_valued>0</is_multi_valued>
    <is_required>0</is_required>
    <item_behavior>float</item_behavior>
    <label xml:lang="en">Change Analyst</label>
    <range_inclusive>0</range_inclusive>
    <readonly>0</readonly>
    <sort_order>768</sort_order>
    <source_id keyed_name="Simple MCO" type="ItemType" name="Simple MCO">2826F2403689438295EDBF60BEAE7C74</source_id>
    <track_history>0</track_history>
    <name>managed_by_id</name>
   </Item>
   <Item type="Property" action="edit" where="source_id='2826F2403689438295EDBF60BEAE7C74' and name='owned_by_id'">
    <column_alignment>left</column_alignment>
    <column_width>120</column_width>
    <data_source keyed_name="Identity" type="ItemType" name="Identity">E582AB17663F4EF28460015B2BE9E094</data_source>
    <data_type>item</data_type>
    <is_hidden>0</is_hidden>
    <is_hidden2>0</is_hidden2>
    <is_indexed>0</is_indexed>
    <is_keyed>0</is_keyed>
    <is_multi_valued>0</is_multi_valued>
    <is_required>0</is_required>
    <item_behavior>float</item_behavior>
    <label xml:lang="en">Originator</label>
    <range_inclusive>0</range_inclusive>
    <readonly>0</readonly>
    <sort_order>640</sort_order>
    <source_id keyed_name="Simple MCO" type="ItemType" name="Simple MCO">2826F2403689438295EDBF60BEAE7C74</source_id>
    <track_history>0</track_history>
    <name>owned_by_id</name>
   </Item>
   <Item type="Property" action="edit" where="source_id='2826F2403689438295EDBF60BEAE7C74' and name='state'">
    <column_alignment>left</column_alignment>
    <column_width>80</column_width>
    <data_type>string</data_type>
    <is_hidden>0</is_hidden>
    <is_hidden2>0</is_hidden2>
    <is_indexed>0</is_indexed>
    <is_keyed>0</is_keyed>
    <is_multi_valued>0</is_multi_valued>
    <is_required>0</is_required>
    <label xml:lang="en">Status</label>
    <range_inclusive>0</range_inclusive>
    <readonly>1</readonly>
    <sort_order>384</sort_order>
    <source_id keyed_name="Simple MCO" type="ItemType" name="Simple MCO">2826F2403689438295EDBF60BEAE7C74</source_id>
    <stored_length>32</stored_length>
    <track_history>0</track_history>
    <name>state</name>
   </Item>
  </Relationships>
 </Item>
</AML>