<AML>
 <Item type="Grid" id="4B9FF34674E34677B877FC8F71B5CDBE" action="add">
  <method keyed_name="History_whereTemplateUsed_grid" type="Method">1E6CB53873B8472A8B69DE4B79457596</method>
  <query><![CDATA[<Item type="History Template" action="History_whereTemplateUsed" id="{id}"/>]]></query>
  <name>History_whereTemplateUsed</name>
  <Relationships>
   <Item type="Grid Column" id="08CD4BA957AE4E6B973BA7B7882AA826" action="add">
    <align>left</align>
    <datatype>default</datatype>
    <label xml:lang="en">ItemType</label>
    <property>name</property>
    <sort_order>100</sort_order>
    <source_id keyed_name="History_whereTemplateUsed" type="Grid">4B9FF34674E34677B877FC8F71B5CDBE</source_id>
    <starts_nested_row>0</starts_nested_row>
    <visible>1</visible>
    <width>200</width>
    <xpath>self::Item[@type="ItemType"]</xpath>
   </Item>
   <Item type="Grid Column" id="6F1044FB2D5C4E369A4F9124FD589976" action="add">
    <align>left</align>
    <datatype>default</datatype>
    <label xml:lang="en">Life Cycle Map</label>
    <property>name</property>
    <sort_order>200</sort_order>
    <source_id keyed_name="History_whereTemplateUsed" type="Grid">4B9FF34674E34677B877FC8F71B5CDBE</source_id>
    <starts_nested_row>1</starts_nested_row>
    <visible>1</visible>
    <width>150</width>
    <xpath>self::Item[@type="ItemType"]/Relationships/Item[@type="ItemType Life Cycle"]/related_id/Item[@type="Life Cycle Map"]</xpath>
   </Item>
   <Item type="Grid Column" id="0C2E70B07F0B4A4F87A2D727B9A27709" action="add">
    <align>left</align>
    <datatype>default</datatype>
    <label xml:lang="en">State</label>
    <property>name</property>
    <sort_order>300</sort_order>
    <source_id keyed_name="History_whereTemplateUsed" type="Grid">4B9FF34674E34677B877FC8F71B5CDBE</source_id>
    <starts_nested_row>1</starts_nested_row>
    <visible>1</visible>
    <width>150</width>
    <xpath>Relationships/Item[@type="Life Cycle State"]</xpath>
   </Item>
  </Relationships>
 </Item>
</AML>