<AML>
 <Item type="PresentationConfiguration" id="09BD716912E647B8A2EBB7A62AA4CA7E" action="add">
  <name>Read-Only Item Attribute</name>
  <Relationships>
   <Item type="PresentationCommandBarSection" id="A7F05B870D974F9D99D8B0158D828B5D" action="add">
    <item_classification />
    <related_id keyed_name="itemview.itemcommandbar.itemattribute" type="CommandBarSection">E380D52290AF4EE4B1E6D95F277DCC90</related_id>
    <role keyed_name="World" type="Identity">A73B655731924CD0B027E4F4D5FCC0A9</role>
    <sort_order>128</sort_order>
    <source_id keyed_name="Read-Only Item Attribute" type="PresentationConfiguration">09BD716912E647B8A2EBB7A62AA4CA7E</source_id>
   </Item>
   <Item type="PresentationCommandBarSection" id="B3DA64BFA9F00B06BDEE61C462534D75" action="add">
    <related_id keyed_name="ac_PolicyAccessItemAttribute_TOC_Content" type="CommandBarSection">B3DA64BFA9F00B06618120D9625E4BB8</related_id>
    <role keyed_name="World" type="Identity">A73B655731924CD0B027E4F4D5FCC0A9</role>
    <sort_order>256</sort_order>
    <source_id keyed_name="Read-Only Item Attribute" type="PresentationConfiguration">09BD716912E647B8A2EBB7A62AA4CA7E</source_id>
   </Item>
  </Relationships>
 </Item>
</AML>