<AML>
 <Item type="Permission" id="05C2A70AB86F4DAAB2DF0C0C42EB632E" action="add">
  <is_private>0</is_private>
  <name>FileGroup</name>
  <Relationships>
   <Item type="Access" id="172F3C5B58B741CB88B46AF0B1179E80" action="add">
    <can_change_access>1</can_change_access>
    <can_delete>1</can_delete>
    <can_discover>1</can_discover>
    <can_get>1</can_get>
    <can_update>1</can_update>
    <related_id keyed_name="File Administrators" type="Identity">4ACA79F318F7448A955AE595511AC789</related_id>
    <show_permissions_warning>1</show_permissions_warning>
    <sort_order>384</sort_order>
    <source_id keyed_name="FileGroup" type="Permission">05C2A70AB86F4DAAB2DF0C0C42EB632E</source_id>
   </Item>
   <Item type="Access" id="A7605782FC554E0D8AF9AB15905372DD" action="add">
    <can_change_access>0</can_change_access>
    <can_delete>0</can_delete>
    <can_discover>1</can_discover>
    <can_get>1</can_get>
    <can_update>0</can_update>
    <related_id keyed_name="Owner" type="Identity">
     <Item type="Identity" action="get" select="id">
      <name>Owner</name>
     </Item>
    </related_id>
    <show_permissions_warning>0</show_permissions_warning>
    <sort_order>256</sort_order>
    <source_id keyed_name="FileGroup" type="Permission">05C2A70AB86F4DAAB2DF0C0C42EB632E</source_id>
   </Item>
  </Relationships>
 </Item>
</AML>